{
 "wiki": "powerrangers.fandom.com",
 "infobox": "Template:TokuHeroInfo",
 "parameters": {
  "image": {
   "_not_set_in": 0,
   "_set_in": 14,
   "Misa Arashiyama": "SunVulcan_ArashiyamaMisa_ShiroBaraKamen.jpg\n",
   "Takuya Yamashiro": " Takuya Yamashiro.jpg\n",
   "Akiko Homura": " Akiko Homura.jpg\n",
   "Haruka Yuuki": " Haruka Yuuki.jpg\n",
   "Tomokazu Daichi": " Tomokazu Daichi.jpg\n",
   "Takeshi Tenma": " Takeshi Tenma.jpg\n",
   "Voicelugger Gold": " Voicelugger gold.jpg\n",
   "Subaru Shibutani": " Subaru Shibutani.jpg\n",
   "Ryo Nishikido": " Ryo Nishikido.jpg\n",
   "Ry\u016bhei Maruyama": " Ry\u016bhei Maruyama.jpg\n",
   "Shota Yasuda": " Shota Yasuda.jpg\n",
   "Tadayoshi \u014ckura": " Tadayoshi \u014ckura.jpg\n",
   "Shingo Murakami": " Shingo Murakami.jpg\n",
   "Yu Yokoyama": " Yu Yokoyama.jpg\n"
  },
  "name": {
   "_not_set_in": 0,
   "_set_in": 14,
   "Misa Arashiyama": " Misa Arashiyama\n",
   "Takuya Yamashiro": " Takuya Yamashiro\n",
   "Akiko Homura": " Akiko Homura\n",
   "Haruka Yuuki": " Haruka Yuuki\n",
   "Tomokazu Daichi": " Tomokazu Daichi\n",
   "Takeshi Tenma": " Takeshi Tenma\n",
   "Voicelugger Gold": " Voicelugger Gold\n",
   "Subaru Shibutani": " Subaru Shibutani\n",
   "Ryo Nishikido": " Ryo Nishikido\n",
   "Ry\u016bhei Maruyama": " Ry\u016bhei Maruyama\n",
   "Shota Yasuda": " Shota Yasuda\n",
   "Tadayoshi \u014ckura": " Tadayoshi \u014ckura\n",
   "Shingo Murakami": " Shingo Murakami\n",
   "Yu Yokoyama": " Yu Yokoyama\n"
  },
  "pic": {
   "_not_set_in": 14,
   "_set_in": 0
  },
  "label": {
   "_not_set_in": 0,
   "_set_in": 14,
   "Misa Arashiyama": "White Rose Mask\n",
   "Takuya Yamashiro": " Spider-Man\n",
   "Akiko Homura": " Voicelugger Ruby\n",
   "Haruka Yuuki": " Voicelugger Rose\n",
   "Tomokazu Daichi": " Voicelugger Emerald\n",
   "Takeshi Tenma": " Voicelugger Sapphire\n",
   "Voicelugger Gold": " Voicelugger Gold\n",
   "Subaru Shibutani": " Red Ranger\n",
   "Ryo Nishikido": " Yellow Ranger\n",
   "Ry\u016bhei Maruyama": " Orange Ranger\n",
   "Shota Yasuda": " Blue Ranger\n",
   "Tadayoshi \u014ckura": " Green Ranger\n",
   "Shingo Murakami": " Purple Ranger\n",
   "Yu Yokoyama": " Black Ranger\n"
  },
  "fullname": {
   "_not_set_in": 13,
   "_set_in": 1,
   "Misa Arashiyama": "undefined\n"
  },
  "sex": {
   "_not_set_in": 1,
   "_set_in": 13,
   "Misa Arashiyama": "Female\n",
   "Akiko Homura": " Female\n",
   "Haruka Yuuki": " Female\n",
   "Tomokazu Daichi": " Male\n",
   "Takeshi Tenma": " Male\n",
   "Voicelugger Gold": " Male\n",
   "Subaru Shibutani": " Male\n",
   "Ryo Nishikido": " Male\n",
   "Ry\u016bhei Maruyama": " Male\n",
   "Shota Yasuda": " Male\n",
   "Tadayoshi \u014ckura": " Male\n",
   "Shingo Murakami": " Male\n",
   "Yu Yokoyama": " Male\n"
  },
  "show": {
   "_not_set_in": 0,
   "_set_in": 14,
   "Misa Arashiyama": "Taiyou Sentai Sun Vulcan\n",
   "Takuya Yamashiro": " Spider-Man\n",
   "Akiko Homura": " Voicelugger\n",
   "Haruka Yuuki": " Voicelugger\n",
   "Tomokazu Daichi": " Voicelugger\n",
   "Takeshi Tenma": " Voicelugger\n",
   "Voicelugger Gold": " Voicelugger\n",
   "Subaru Shibutani": " Kanjani Sentai Eightranger\n",
   "Ryo Nishikido": " Kanjani Sentai Eightranger\n",
   "Ry\u016bhei Maruyama": " Kanjani Sentai Eightranger\n",
   "Shota Yasuda": " Kanjani Sentai Eightranger\n",
   "Tadayoshi \u014ckura": " Kanjani Sentai Eightranger\n",
   "Shingo Murakami": " Kanjani Sentai Eightranger\n",
   "Yu Yokoyama": " Kanjani Sentai Eightranger\n"
  },
  "color": {
   "_not_set_in": 0,
   "_set_in": 14,
   "Misa Arashiyama": "White\n",
   "Takuya Yamashiro": " Red\n",
   "Akiko Homura": " Red\n",
   "Haruka Yuuki": " Pink\n",
   "Tomokazu Daichi": " Green\n",
   "Takeshi Tenma": " Blue\n",
   "Voicelugger Gold": " Gold\n",
   "Subaru Shibutani": " Red\n",
   "Ryo Nishikido": " Yellow\n",
   "Ry\u016bhei Maruyama": " Orange\n",
   "Shota Yasuda": " Blue\n",
   "Tadayoshi \u014ckura": " Green\n",
   "Shingo Murakami": " Purple\n",
   "Yu Yokoyama": " Black\n"
  },
  "homeworld": {
   "_not_set_in": 0,
   "_set_in": 14,
   "Misa Arashiyama": "[[Earth]]\n",
   "Takuya Yamashiro": " [[Earth]]\n",
   "Akiko Homura": " [[Earth]]\n",
   "Haruka Yuuki": " [[Earth]]\n",
   "Tomokazu Daichi": " [[Earth]]\n",
   "Takeshi Tenma": " [[Earth]]\n",
   "Voicelugger Gold": " [[Earth]]\n",
   "Subaru Shibutani": " [[Earth]]\n",
   "Ryo Nishikido": " [[Earth]]\n",
   "Ry\u016bhei Maruyama": " [[Earth]]\n",
   "Shota Yasuda": " [[Earth]]\n",
   "Tadayoshi \u014ckura": " [[Earth]]\n",
   "Shingo Murakami": " [[Earth]]\n",
   "Yu Yokoyama": " [[Earth]]\n"
  },
  "firstepisode": {
   "_not_set_in": 0,
   "_set_in": 14,
   "Misa Arashiyama": "[[Ep. 1: The Machine Empire of the North Pole]]\n",
   "Takuya Yamashiro": " [[The Time of Revenge Has Come! Beat Down Iron Cross Group!!]]\n",
   "Akiko Homura": " [[I am a Hero]]\n",
   "Haruka Yuuki": " [[I am a Hero]]\n",
   "Tomokazu Daichi": " [[I am a Hero]]\n",
   "Takeshi Tenma": " [[I am a Hero]]\n",
   "Voicelugger Gold": " [[I am a Hero]]\n",
   "Subaru Shibutani": "\n",
   "Ryo Nishikido": "\n",
   "Ry\u016bhei Maruyama": "\n",
   "Shota Yasuda": "\n",
   "Tadayoshi \u014ckura": "\n",
   "Shingo Murakami": "\n",
   "Yu Yokoyama": "\n"
  },
  "lastepisode": {
   "_not_set_in": 0,
   "_set_in": 14,
   "Misa Arashiyama": "[[Final Ep.: Shine, North Pole Aurora]]\n",
   "Takuya Yamashiro": " [[The Hero's Shining Hot Blood]]\n",
   "Akiko Homura": " [[Smiling Face in Rain, Clear Weather in a Smiling Face]]\n",
   "Haruka Yuuki": " [[Smiling Face in Rain, Clear Weather in a Smiling Face]]\n",
   "Tomokazu Daichi": " [[Smiling Face in Rain, Clear Weather in a Smiling Face]]\n",
   "Takeshi Tenma": " [[Smiling Face in Rain, Clear Weather in a Smiling Face]]\n",
   "Voicelugger Gold": " [[Smiling Face in Rain, Clear Weather in a Smiling Face]]\n",
   "Subaru Shibutani": "\n",
   "Ryo Nishikido": "\n",
   "Ry\u016bhei Maruyama": "\n",
   "Shota Yasuda": "\n",
   "Tadayoshi \u014ckura": "\n",
   "Shingo Murakami": "\n",
   "Yu Yokoyama": "\n"
  },
  "numberofepisodes": {
   "_not_set_in": 0,
   "_set_in": 14,
   "Misa Arashiyama": "50 episodes, 1 movie\n",
   "Takuya Yamashiro": " 41 (episodes)<br>1 (movie)\n",
   "Akiko Homura": " 12\n",
   "Haruka Yuuki": " 12\n",
   "Tomokazu Daichi": " 12\n",
   "Takeshi Tenma": " 12\n",
   "Voicelugger Gold": " 12\n",
   "Subaru Shibutani": "\n",
   "Ryo Nishikido": "\n",
   "Ry\u016bhei Maruyama": "\n",
   "Shota Yasuda": "\n",
   "Tadayoshi \u014ckura": "\n",
   "Shingo Murakami": "\n",
   "Yu Yokoyama": "\n"
  },
  "cast": {
   "_not_set_in": 12,
   "_set_in": 2,
   "Misa Arashiyama": "Yumi Nemoto\n",
   "Takuya Yamashiro": " Shinji T\u014dd\u014d\n"
  },
  "casts": {
   "_not_set_in": 2,
   "_set_in": 12,
   "Akiko Homura": " [[Akiko Nakagawa]]\n",
   "Haruka Yuuki": " [[Haruna Ikezawa]]\n",
   "Tomokazu Daichi": " [[Tomokazu Seki]]\n",
   "Takeshi Tenma": " [[Takeshi Kusao]]\n",
   "Voicelugger Gold": " [[Ichirou Mizuki]]",
   "Subaru Shibutani": " Himself\n",
   "Ryo Nishikido": " Himself\n",
   "Ry\u016bhei Maruyama": " Himself\n",
   "Shota Yasuda": " Himself\n",
   "Tadayoshi \u014ckura": " Himself\n",
   "Shingo Murakami": " Himself\n",
   "Yu Yokoyama": " Himself\n"
  },
  "image2": {
   "_not_set_in": 0,
   "_set_in": 14,
   "Misa Arashiyama": "SunVulcan_ShiroBaraKamen_ArashiyamaMisa.jpg\n",
   "Takuya Yamashiro": " Spider-Man.jpg\n",
   "Akiko Homura": " Voicelugger Ruby.jpg\n",
   "Haruka Yuuki": " Voicelugger Rose.jpg\n",
   "Tomokazu Daichi": " Voicelugger Emerald.jpg\n",
   "Takeshi Tenma": " Voicelugger Sapphire.jpg\n",
   "Voicelugger Gold": " Voicelugger Gold.jpg\n",
   "Subaru Shibutani": " \n",
   "Ryo Nishikido": " \n",
   "Ry\u016bhei Maruyama": " \n",
   "Shota Yasuda": " \n",
   "Tadayoshi \u014ckura": " \n",
   "Shingo Murakami": " \n",
   "Yu Yokoyama": " \n"
  }
 }
}