{
 "wiki": "steven-universe.fandom.com",
 "infobox": "Template:Userinfo",
 "parameters": {
  "BGColor": {
   "_not_set_in": 0,
   "_set_in": 0
  },
  "BorderColor": {
   "_not_set_in": 0,
   "_set_in": 0
  },
  "FontColor": {
   "_not_set_in": 0,
   "_set_in": 0
  },
  "Title": {
   "_not_set_in": 0,
   "_set_in": 0
  },
  "image": {
   "_not_set_in": 0,
   "_set_in": 0
  },
  "Voicedby": {
   "_not_set_in": 0,
   "_set_in": 0
  },
  "Species": {
   "_not_set_in": 0,
   "_set_in": 0
  },
  "Gender": {
   "_not_set_in": 0,
   "_set_in": 0
  },
  "Age": {
   "_not_set_in": 0,
   "_set_in": 0
  },
  "Nicknames": {
   "_not_set_in": 0,
   "_set_in": 0
  },
  "Friends": {
   "_not_set_in": 0,
   "_set_in": 0
  },
  "Occupation": {
   "_not_set_in": 0,
   "_set_in": 0
  },
  "Affiliation": {
   "_not_set_in": 0,
   "_set_in": 0
  },
  "Residence": {
   "_not_set_in": 0,
   "_set_in": 0
  },
  "Birthday": {
   "_not_set_in": 0,
   "_set_in": 0
  },
  "FirstAppearance": {
   "_not_set_in": 0,
   "_set_in": 0
  },
  "OtherAppearances": {
   "_not_set_in": 0,
   "_set_in": 0
  }
 }
}